btmodified/__init__.py
btmodified/_btmodified.py
btmodified/_ctfidf.py
btmodified/_embeddings.py
btmodified/_mmr.py
btmodified/_utils.py
btmodified-0.6.0.dist-info/LICENSE
btmodified-0.6.0.dist-info/METADATA
btmodified-0.6.0.dist-info/WHEEL
btmodified-0.6.0.dist-info/top_level.txt
btmodified-0.6.0.dist-info/RECORD
