Metadata-Version: 2.1
Name: btmodified
Version: 0.6.0
Summary: Modified version of Bertopics
Home-page: https://github.com/Israel-osorio-ortiz/BERTmodified
Author: Unknown
Author-email: israel.osorioo@outlook.com
License: UNKNOWN
Keywords: none
Platform: UNKNOWN
Classifier: Programming Language :: Python
Classifier: Intended Audience :: Science/Research
Classifier: Intended Audience :: Developers
Classifier: Topic :: Scientific/Engineering :: Artificial Intelligence
Classifier: License :: OSI Approved :: MIT License
Classifier: Topic :: Scientific/Engineering
Classifier: Operating System :: Microsoft :: Windows
Classifier: Operating System :: POSIX
Classifier: Operating System :: Unix
Classifier: Operating System :: MacOS
Classifier: Programming Language :: Python :: 3.7
Classifier: Programming Language :: Python :: 3.6
Classifier: Programming Language :: Python :: 3.8
Requires-Python: >=3.6
Requires-Dist: numpy (>=1.19.2)
Requires-Dist: umap-learn (>=0.5.0)
Requires-Dist: pandas (>=1.1.5)
Requires-Dist: scikit-learn (>=0.22.2.post1)
Requires-Dist: tqdm (>=4.41.1)
Requires-Dist: torch (>=1.4.0)
Requires-Dist: sentence-transformers (>=0.4.1)
Provides-Extra: all
Requires-Dist: matplotlib (>=3.2.2) ; extra == 'all'
Requires-Dist: plotly (<4.14.3,>=4.7.0) ; extra == 'all'
Requires-Dist: flair (==0.7) ; extra == 'all'
Provides-Extra: dev
Requires-Dist: mkdocs (>=1.1) ; extra == 'dev'
Requires-Dist: mkdocs-material (>=4.6.3) ; extra == 'dev'
Requires-Dist: mkdocstrings (>=0.8.0) ; extra == 'dev'
Requires-Dist: pytest (>=5.4.3) ; extra == 'dev'
Requires-Dist: pytest-cov (>=2.6.1) ; extra == 'dev'
Requires-Dist: matplotlib (>=3.2.2) ; extra == 'dev'
Requires-Dist: plotly (<4.14.3,>=4.7.0) ; extra == 'dev'
Requires-Dist: flair (==0.7) ; extra == 'dev'
Provides-Extra: docs
Requires-Dist: mkdocs (>=1.1) ; extra == 'docs'
Requires-Dist: mkdocs-material (>=4.6.3) ; extra == 'docs'
Requires-Dist: mkdocstrings (>=0.8.0) ; extra == 'docs'
Provides-Extra: flair
Requires-Dist: flair (==0.7) ; extra == 'flair'
Provides-Extra: test
Requires-Dist: pytest (>=5.4.3) ; extra == 'test'
Requires-Dist: pytest-cov (>=2.6.1) ; extra == 'test'
Provides-Extra: visualization
Requires-Dist: matplotlib (>=3.2.2) ; extra == 'visualization'
Requires-Dist: plotly (<4.14.3,>=4.7.0) ; extra == 'visualization'
